src/ALU.sv
`timescale 1ns/1ps

module ALU (
  input logic   [7:0] IN_A,
  input logic   [7:0] IN_R,
  input logic   [2:0] IN_OP,
  output logic  [7:0] OUT_A,
  output logic        OUT_CY
);

typedef enum logic [2:0] { 
  ADD = 3'b000, 
  SUB = 3'b001, 
  OR  = 3'b010, 
  AND = 3'b011, 
  XOR = 3'b100, 
  NOT = 3'b101, 
  LD  = 3'b110 
  } OP_CODE;

always_comb begin : ALU
  OUT_CY = 0;
  OUT_A = 8'b0;
  case (IN_OP)
    ADD : begin
      {OUT_CY, OUT_A} = IN_A + IN_R;
    end 
    SUB : begin
      {OUT_CY, OUT_A} = IN_A - IN_R;
    end
    OR : begin
      OUT_CY = 0;
      OUT_A = IN_A | IN_R;
    end
    AND : begin
      OUT_CY = 0;
      OUT_A = IN_A & IN_R;
    end
    XOR : begin
      OUT_CY = 0;
      OUT_A = IN_A ^ IN_R;
    end
    NOT : begin
      OUT_CY = 0;
      OUT_A = ~IN_A;
    end
    LD : begin
      OUT_A = IN_R;
    end
    default : begin
      OUT_CY = 0;
      OUT_A = 8'b0;
    end 
  endcase
end
  
endmodule

verif/ALU_tb.sv
`timescale 1ns/1ps

module ALU_tb;
    logic [7:0] A_t;
    logic [7:0] R_t;
    logic [2:0] OP_t;
    logic [7:0] OUT_t;
    logic CY_t;

ALU uut (
    .IN_A(A_t),
    .IN_R(R_t),
    .IN_OP(OP_t),
    .OUT_A(OUT_t),
    .OUT_CY(CY_t)
);

initial begin
    $display("ALU Testbench...");

    //Reset
    A_t = 8'd0; R_t = 8'd0; OP_t = 3'd0; #5

    //ADD test
    A_t = 8'b11111111; R_t = 8'b00000001; OP_t = 3'b000; #10;
    $display("ADD: %d + %d = %d, CY = %b", A_t, R_t, OUT_t, CY_t);

    //SUB test
    A_t = 8'd0; R_t = 8'd1; OP_t = 3'b001; #10;
    $display("SUB: %d - %d = %d, CY = %b", A_t, R_t, OUT_t, CY_t);

    //OR test
    A_t = 8'b10101010; R_t = 8'b01010101; OP_t = 3'b010; #10;
    $display("OR: %b | %b = %b, CY = %b", A_t, R_t, OUT_t, CY_t);

    //AND test
    A_t = 8'b10101010; R_t = 8'b01010101; OP_t = 3'b011; #10;
    $display("AND: %b & %b = %b, CY = %b", A_t, R_t, OUT_t, CY_t);

    //XOR test
    A_t = 8'b10101010; R_t = 8'b01010101; OP_t = 3'b100; #10;
    $display("XOR: %b ^ %b = %b, CY = %b", A_t, R_t, OUT_t, CY_t);

    //NOT test
    A_t = 8'b00111100; R_t = 8'b01010101; OP_t = 3'b101; #10;
    $display("NOT: %b = ~%b, CY = %b", A_t, OUT_t, CY_t);

    //LD test
    A_t = 8'b11110000; R_t = 8'b00001111; OP_t = 3'b110; #10;
    $display("LD: %b = %b, CY = %b", R_t, OUT_t, CY_t);

    $finish;
end

initial begin
	$dumpfile("alu.vcd");
	$dumpvars();	
end
    
endmodule

alu.vcd
$date
	Mon Feb 03 17:05:03 2025
$end
$version
	Icarus Verilog
$end
$timescale
	1ps
$end
$scope module ALU_tb $end
$var wire 8 ! OUT_t [7:0] $end
$var wire 1 " CY_t $end
$var reg 8 # A_t [7:0] $end
$var reg 3 $ OP_t [2:0] $end
$var reg 8 % R_t [7:0] $end
$scope module uut $end
$var wire 8 & IN_A [7:0] $end
$var wire 3 ' IN_OP [2:0] $end
$var wire 8 ( IN_R [7:0] $end
$var reg 8 ) OUT_A [7:0] $end
$var reg 1 " OUT_CY $end
$scope begin ALU $end
$upscope $end
$upscope $end
$upscope $end
$enddefinitions $end
$comment Show the parameter values. $end
$dumpall
$end
#0
$dumpvars
b0 )
b0 (
b0 '
b0 &
b0 %
b0 $
b0 #
0"
b0 !
$end
#5000
1"
b1 %
b1 (
b11111111 #
b11111111 &
#15000
b11111111 !
b11111111 )
1"
b1 $
b1 '
b0 #
b0 &
#25000
b11111111 !
b11111111 )
0"
b10 $
b10 '
b1010101 %
b1010101 (
b10101010 #
b10101010 &
#35000
b0 !
b0 )
b11 $
b11 '
#45000
b11111111 !
b11111111 )
b100 $
b100 '
#55000
b11000011 !
b11000011 )
b101 $
b101 '
b111100 #
b111100 &
#65000
b1111 !
b1111 )
b110 $
b110 '
b1111 %
b1111 (
b11110000 #
b11110000 &
