src/PM.sv
`timescale 1ns/1ps

module PM #(
    parameter DATA_WIDTH = 16
) 
(
    input logic [4:0] PM_IN,
    output logic [DATA_WIDTH-1:0] PM_OUT
);

logic [DATA_WIDTH-1:0] MEM [0:31]; 

initial begin
    MEM[0] = 16'b0000_00_0000000000;
    MEM[1] = 16'b0000_0000000000_00;
    MEM[2] = 16'b0000_00000_0000000;
    MEM[3] = 16'b101010;
    MEM[4] = 16'b010101;
    MEM[5] = 16'b111111;

    for (int i = 6; i < 32 ; i++) begin
        MEM[i] = 16'b1010_00; //NOP
    end
end

assign PM_OUT = MEM[PM_IN];
    
endmodule

/*

Instructions:
    Regular:
        4-bit OP_CODE | 4-bit reg_code | 8-bit value
    JMP case:
        4-bit OP_CODE | 4-bit reg_code | 5-bit PC addres | 3-bit reserved


OP_code:
    0000 - ADD
    0001 - SUB
    0010 - OR
    0011 - AND
    0100 - XOR
    0101 - NOT
    0110 - ST
    0111 - LD
    1000 -
    1001 -
    1010 - NOP
    1011 - 
    1100 - 
    1101 - 
    1110 - 
    1111 - JMP

reg_code:
    0000 - R0
    0001 - R1
    0010 - R2
    0011 - R3
    0100 - ID
    0101 -
    0110 -
    0111 -
    1000 - 
    1001 -
    1010 -
    1011 -
    1100 - DM0
    1101 - DM1
    1110 - DM2
    1111 - DM3
*/

src/PC.sv
`timescale 1ns/1ps

module PC (
    input logic CLK,
    input logic RST,
    output logic [4:0] PC_OUT
);
    
always_ff @( posedge CLK or posedge RST ) begin : PC
    if (RST) begin
        PC_OUT <= '0;
    end else begin
        PC_OUT <= PC_OUT + 1;
    end
end

endmodule

verif/PC_PM_tb.sv
`timescale 1ns/1ps

module PC_PM_tb;

logic CLK;
logic RST;
logic [5:0] PM_OUT_tb;

logic [4:0] PC_PM;

PC pc_uut(
    .CLK(CLK),
    .RST(RST),
    .PC_OUT(PC_PM)
);

PM pm_uut(
    .PM_IN(PC_PM),
    .PM_OUT(PM_OUT_tb)
);

always #5 CLK = ~CLK;

initial begin
    $display("PC_PM Testbench...");

    //Reset
    CLK = 0; RST = 1; #10;
    RST = 0;

    #1000;
    $finish;
end

initial begin
	$dumpfile("pc_pm.vcd");
	$dumpvars();	
end

endmodule

pc.vcd
$date
	Mon Feb 17 14:11:26 2025
$end
$version
	Icarus Verilog
$end
$timescale
	1ps
$end
$scope module PC_PM_tb $end
$var wire 6 ! PM_OUT_tb [5:0] $end
$var wire 5 " PC_PM [4:0] $end
$var reg 1 # CLK $end
$var reg 1 $ RST $end
$scope module pc_uut $end
$var wire 1 # CLK $end
$var wire 1 $ RST $end
$var reg 5 % PC_OUT [4:0] $end
$scope begin PC $end
$upscope $end
$upscope $end
$scope module pm_uut $end
$var wire 5 & PM_IN [4:0] $end
$var wire 6 ' PM_OUT [5:0] $end
$var parameter 32 ( DATA_WIDTH $end
$upscope $end
$upscope $end
$enddefinitions $end
$comment Show the parameter values. $end
$dumpall
b110 (
$end
#0
$dumpvars
b0 '
b0 &
b0 %
1$
0#
b0 "
b0 !
$end
#5000
1#
#10000
0#
0$
#15000
b111000 !
b111000 '
b1 "
b1 %
b1 &
1#
#20000
0#
#25000
b10110 !
b10110 '
b10 "
b10 %
b10 &
1#
#30000
0#
#35000
b101010 !
b101010 '
b11 "
b11 %
b11 &
1#
#40000
0#
#45000
b10101 !
b10101 '
b100 "
b100 %
b100 &
1#
#50000
0#
#55000
b111111 !
b111111 '
b101 "
b101 %
b101 &
1#
#60000
0#
#65000
bx !
bx '
b110 "
b110 %
b110 &
1#
#70000
0#
#75000
b111 "
b111 %
b111 &
1#
#80000
0#
#85000
b1000 "
b1000 %
b1000 &
1#
#90000
0#
#95000
b1001 "
b1001 %
b1001 &
1#
#100000
0#
#105000
b1010 "
b1010 %
b1010 &
1#
#110000
0#
#115000
b1011 "
b1011 %
b1011 &
1#
#120000
0#
#125000
b1100 "
b1100 %
b1100 &
1#
#130000
0#
#135000
b1101 "
b1101 %
b1101 &
1#
#140000
0#
#145000
b1110 "
b1110 %
b1110 &
1#
#150000
0#
#155000
b1111 "
b1111 %
b1111 &
1#
#160000
0#
#165000
b10000 "
b10000 %
b10000 &
1#
#170000
0#
#175000
b10001 "
b10001 %
b10001 &
1#
#180000
0#
#185000
b10010 "
b10010 %
b10010 &
1#
#190000
0#
#195000
b10011 "
b10011 %
b10011 &
1#
#200000
0#
#205000
b10100 "
b10100 %
b10100 &
1#
#210000
0#
#215000
b10101 "
b10101 %
b10101 &
1#
#220000
0#
#225000
b10110 "
b10110 %
b10110 &
1#
#230000
0#
#235000
b10111 "
b10111 %
b10111 &
1#
#240000
0#
#245000
b11000 "
b11000 %
b11000 &
1#
#250000
0#
#255000
b11001 "
b11001 %
b11001 &
1#
#260000
0#
#265000
b11010 "
b11010 %
b11010 &
1#
#270000
0#
#275000
b11011 "
b11011 %
b11011 &
1#
#280000
0#
#285000
b11100 "
b11100 %
b11100 &
1#
#290000
0#
#295000
b11101 "
b11101 %
b11101 &
1#
#300000
0#
#305000
b11110 "
b11110 %
b11110 &
1#
#310000
0#
#315000
b11111 "
b11111 %
b11111 &
1#
#320000
0#
#325000
b0 !
b0 '
b0 "
b0 %
b0 &
1#
#330000
0#
#335000
b111000 !
b111000 '
b1 "
b1 %
b1 &
1#
#340000
0#
#345000
b10110 !
b10110 '
b10 "
b10 %
b10 &
1#
#350000
0#
#355000
b101010 !
b101010 '
b11 "
b11 %
b11 &
1#
#360000
0#
#365000
b10101 !
b10101 '
b100 "
b100 %
b100 &
1#
#370000
0#
#375000
b111111 !
b111111 '
b101 "
b101 %
b101 &
1#
#380000
0#
#385000
bx !
bx '
b110 "
b110 %
b110 &
1#
#390000
0#
#395000
b111 "
b111 %
b111 &
1#
#400000
0#
#405000
b1000 "
b1000 %
b1000 &
1#
#410000
0#
#415000
b1001 "
b1001 %
b1001 &
1#
#420000
0#
#425000
b1010 "
b1010 %
b1010 &
1#
#430000
0#
#435000
b1011 "
b1011 %
b1011 &
1#
#440000
0#
#445000
b1100 "
b1100 %
b1100 &
1#
#450000
0#
#455000
b1101 "
b1101 %
b1101 &
1#
#460000
0#
#465000
b1110 "
b1110 %
b1110 &
1#
#470000
0#
#475000
b1111 "
b1111 %
b1111 &
1#
#480000
0#
#485000
b10000 "
b10000 %
b10000 &
1#
#490000
0#
#495000
b10001 "
b10001 %
b10001 &
1#
#500000
0#
#505000
b10010 "
b10010 %
b10010 &
1#
#510000
0#
#515000
b10011 "
b10011 %
b10011 &
1#
#520000
0#
#525000
b10100 "
b10100 %
b10100 &
1#
#530000
0#
#535000
b10101 "
b10101 %
b10101 &
1#
#540000
0#
#545000
b10110 "
b10110 %
b10110 &
1#
#550000
0#
#555000
b10111 "
b10111 %
b10111 &
1#
#560000
0#
#565000
b11000 "
b11000 %
b11000 &
1#
#570000
0#
#575000
b11001 "
b11001 %
b11001 &
1#
#580000
0#
#585000
b11010 "
b11010 %
b11010 &
1#
#590000
0#
#595000
b11011 "
b11011 %
b11011 &
1#
#600000
0#
#605000
b11100 "
b11100 %
b11100 &
1#
#610000
0#
#615000
b11101 "
b11101 %
b11101 &
1#
#620000
0#
#625000
b11110 "
b11110 %
b11110 &
1#
#630000
0#
#635000
b11111 "
b11111 %
b11111 &
1#
#640000
0#
#645000
b0 !
b0 '
b0 "
b0 %
b0 &
1#
#650000
0#
#655000
b111000 !
b111000 '
b1 "
b1 %
b1 &
1#
#660000
0#
#665000
b10110 !
b10110 '
b10 "
b10 %
b10 &
1#
#670000
0#
#675000
b101010 !
b101010 '
b11 "
b11 %
b11 &
1#
#680000
0#
#685000
b10101 !
b10101 '
b100 "
b100 %
b100 &
1#
#690000
0#
#695000
b111111 !
b111111 '
b101 "
b101 %
b101 &
1#
#700000
0#
#705000
bx !
bx '
b110 "
b110 %
b110 &
1#
#710000
0#
#715000
b111 "
b111 %
b111 &
1#
#720000
0#
#725000
b1000 "
b1000 %
b1000 &
1#
#730000
0#
#735000
b1001 "
b1001 %
b1001 &
1#
#740000
0#
#745000
b1010 "
b1010 %
b1010 &
1#
#750000
0#
#755000
b1011 "
b1011 %
b1011 &
1#
#760000
0#
#765000
b1100 "
b1100 %
b1100 &
1#
#770000
0#
#775000
b1101 "
b1101 %
b1101 &
1#
#780000
0#
#785000
b1110 "
b1110 %
b1110 &
1#
#790000
0#
#795000
b1111 "
b1111 %
b1111 &
1#
#800000
0#
#805000
b10000 "
b10000 %
b10000 &
1#
#810000
0#
#815000
b10001 "
b10001 %
b10001 &
1#
#820000
0#
#825000
b10010 "
b10010 %
b10010 &
1#
#830000
0#
#835000
b10011 "
b10011 %
b10011 &
1#
#840000
0#
#845000
b10100 "
b10100 %
b10100 &
1#
#850000
0#
#855000
b10101 "
b10101 %
b10101 &
1#
#860000
0#
#865000
b10110 "
b10110 %
b10110 &
1#
#870000
0#
#875000
b10111 "
b10111 %
b10111 &
1#
#880000
0#
#885000
b11000 "
b11000 %
b11000 &
1#
#890000
0#
#895000
b11001 "
b11001 %
b11001 &
1#
#900000
0#
#905000
b11010 "
b11010 %
b11010 &
1#
#910000
0#
#915000
b11011 "
b11011 %
b11011 &
1#
#920000
0#
#925000
b11100 "
b11100 %
b11100 &
1#
#930000
0#
#935000
b11101 "
b11101 %
b11101 &
1#
#940000
0#
#945000
b11110 "
b11110 %
b11110 &
1#
#950000
0#
#955000
b11111 "
b11111 %
b11111 &
1#
#960000
0#
#965000
b0 !
b0 '
b0 "
b0 %
b0 &
1#
#970000
0#
#975000
b111000 !
b111000 '
b1 "
b1 %
b1 &
1#
#980000
0#
#985000
b10110 !
b10110 '
b10 "
b10 %
b10 &
1#
#990000
0#
#995000
b101010 !
b101010 '
b11 "
b11 %
b11 &
1#
#1000000
0#
#1005000
b10101 !
b10101 '
b100 "
b100 %
b100 &
1#
