src/RF.sv
`timescale 1ns/1ps

module RF (
    input logic CLK,            //Clock
    input logic RST,            //Reset
    input logic RF_EN,          //Register enable
    input logic [1:0] RF_ADDR,  //Register address
    input logic [7:0] RF_IN,    //Data in
    output logic [7:0] RF_OUT   //Data out
);

logic [7:0] Registers [0:3]; //Registers declaration

always_ff @( posedge CLK or posedge RST ) begin : RF
    if (RST) begin
        for (int i = 0; i < 4 ; i++ ) begin //Reset condition in regiser file
            Registers[i] <= '0; 
        end
    end else if (RF_EN) begin
        Registers[RF_ADDR] <= RF_IN; //Enable specify register to make store operation
    end
end
    
assign RF_OUT = Registers[RF_ADDR]; //Assigned selected register

endmodule

verif/RF_tb.sv
`timescale 1ns/1ps

module RF_tb;
    logic CLK;
    logic RST;
    logic RF_EN_t;
    logic [1:0] RF_ADDR_t;
    logic [7:0] RF_IN_t;
    logic [7:0] RF_OUT_t;

RF uut(
    .CLK(CLK),
    .RST(RST),
    .RF_EN(RF_EN_t),
    .RF_ADDR(RF_ADDR_t),
    .RF_IN(RF_IN_t),
    .RF_OUT(RF_OUT_t)
);

always #5 CLK = ~CLK;

initial begin
    $display("RF Testbench...");
    //Reset
    CLK = 0; RST = 1; RF_IN_t = '0; #10;
    RST = 0;

    RF_ADDR_t = 2'b00;
    RF_EN_t = 1;
    RF_IN_t = 8'hAA;
    #20;
    RF_IN_t = 8'h00;
    RF_EN_t = 0;
    #20;
    RF_ADDR_t = 2'b01;
    #20;
    RF_EN_t = 1;
    #20;
    RF_IN_t = 8'hFF;
    #20;
    RF_IN_t = 8'h00;
    RF_EN_t = 0;
    #20;
    RF_ADDR_t = 2'b00;
    #20;
    RF_EN_t = 1;
    #20;

    $finish;
end

initial begin
	$dumpfile("rf.vcd");
	$dumpvars();	
end

endmodule

rf.vcd
$date
	Mon Feb 17 11:08:34 2025
$end
$version
	Icarus Verilog
$end
$timescale
	1ps
$end
$scope module RF_tb $end
$var wire 8 ! RF_OUT_t [7:0] $end
$var reg 1 " CLK $end
$var reg 2 # RF_ADDR_t [1:0] $end
$var reg 1 $ RF_EN_t $end
$var reg 8 % RF_IN_t [7:0] $end
$var reg 1 & RST $end
$scope module uut $end
$var wire 1 " CLK $end
$var wire 2 ' RF_ADDR [1:0] $end
$var wire 1 $ RF_EN $end
$var wire 8 ( RF_IN [7:0] $end
$var wire 8 ) RF_OUT [7:0] $end
$var wire 1 & RST $end
$scope begin RF $end
$scope begin $ivl_for_loop0 $end
$var integer 32 * i [31:0] $end
$upscope $end
$upscope $end
$upscope $end
$upscope $end
$enddefinitions $end
$comment Show the parameter values. $end
$dumpall
$end
#0
$dumpvars
b100 *
bx )
b0 (
bx '
1&
b0 %
x$
bx #
0"
bx !
$end
#5000
b100 *
1"
#10000
0"
b10101010 %
b10101010 (
1$
b0 !
b0 )
b0 #
b0 '
0&
#15000
b10101010 !
b10101010 )
1"
#20000
0"
#25000
1"
#30000
0"
0$
b0 %
b0 (
#35000
1"
#40000
0"
#45000
1"
#50000
0"
b0 !
b0 )
b1 #
b1 '
#55000
1"
#60000
0"
#65000
1"
#70000
0"
1$
#75000
1"
#80000
0"
#85000
1"
#90000
0"
b11111111 %
b11111111 (
#95000
b11111111 !
b11111111 )
1"
#100000
0"
#105000
1"
#110000
0"
0$
b0 %
b0 (
#115000
1"
#120000
0"
#125000
1"
#130000
0"
b10101010 !
b10101010 )
b0 #
b0 '
#135000
1"
#140000
0"
#145000
1"
#150000
0"
1$
#155000
b0 !
b0 )
1"
